spytnik/__init__.py
spytnik/sats.py
spytnik/sites.py
spytnik/spytnik.py
spytnik/traces.py
spytnik/widgets/__init__.py
spytnik/widgets/map.py
spytnik/widgets/polarplot.py
spytnik-0.0.1.dist-info/LICENSE
spytnik-0.0.1.dist-info/METADATA
spytnik-0.0.1.dist-info/WHEEL
spytnik-0.0.1.dist-info/entry_points.txt
spytnik-0.0.1.dist-info/top_level.txt
spytnik-0.0.1.dist-info/RECORD
